{
    "database": [
        {
            "ejecutivo": "",
            "nombre": "Magdalena De La Fuente",
            "rut": "204443092",
            "solicitudes": [
                "{\n    \"antecedentes\": \"tu nueva clave es JIJIJAJA\",\n    \"ident\": \"03\",\n    \"state\": true,\n    \"subject\": \"cambio de clave wifi\"\n}",
                "{\n    \"antecedentes\": \"no hay moneas\",\n    \"ident\": \"04\",\n    \"state\": true,\n    \"subject\": \"cancelacion de plan de datos\"\n}"
            ]
        },
        {
            "ejecutivo": "",
            "nombre": "Melanie Fernandez",
            "rut": "10101010",
            "solicitudes": [
                "{\n    \"antecedentes\": \"Tu nueva clave es abcdeafds\",\n    \"ident\": \"01\",\n    \"state\": true,\n    \"subject\": \"actualizacion de plan de internet\"\n}",
                "{\n    \"antecedentes\": \"\",\n    \"ident\": \"02\",\n    \"state\": true,\n    \"subject\": \"cambio de clave wifi\"\n}"
            ]
        },
        {
            "ejecutivo": "",
            "nombre": "Paola Nessi",
            "rut": "202020202",
            "solicitudes": [
                "{\n    \"antecedentes\": \"tu nueva clave es jutsuuu\",\n    \"ident\": \"01\",\n    \"state\": true,\n    \"subject\": \"cambio de clave wifi\"\n}",
                "{\n    \"antecedentes\": \"mama ven a buscarme\",\n    \"ident\": \"02\",\n    \"state\": true,\n    \"subject\": \"cancelacion de plan de datos\"\n}"
            ]
        },
        {
            "ejecutivo": "",
            "nombre": "Kayne West",
            "rut": "303030303",
            "solicitudes": [
                "{\n    \"antecedentes\": \"\",\n    \"ident\": \"01\",\n    \"state\": true,\n    \"subject\": \"actualizacion de plan de internet\"\n}",
                "{\n    \"antecedentes\": \"\",\n    \"ident\": \"02\",\n    \"state\": true,\n    \"subject\": \"cambio de clave wifi\"\n}"
            ]
        },
        {
            "ejecutivo": "",
            "nombre": "Tony Stark",
            "rut": "300030003",
            "solicitudes": [
                "{\n    \"antecedentes\": \"tu nueva clave es JIJIJAJA\",\n    \"ident\": \"03\",\n    \"state\": true,\n    \"subject\": \"cambio de clave wifi\"\n}",
                "{\n    \"antecedentes\": \"mama ven a buscarme\",\n    \"ident\": \"04\",\n    \"state\": true,\n    \"subject\": \"cancelacion de plan de datos\"\n}"
            ]
        },
        {
            "ejecutivo": "",
            "nombre": "Bruce Banner",
            "rut": "707070707",
            "solicitudes": [
                "{\n    \"antecedentes\": \"\",\n    \"ident\": \"01\",\n    \"state\": true,\n    \"subject\": \"actualizacion de plan de internet\"\n}",
                "{\n    \"antecedentes\": \"\",\n    \"ident\": \"02\",\n    \"state\": true,\n    \"subject\": \"cambio de clave wifi\"\n}"
            ]
        },
        {
            "ejecutivo": "",
            "nombre": "Doc Oc",
            "rut": "808080808",
            "solicitudes": [
                "{\n    \"antecedentes\": \"Tu nueva clave es JIJIJAJA\",\n    \"ident\": \"01\",\n    \"state\": true,\n    \"subject\": \"cambio de clave wifi\"\n}",
                "{\n    \"antecedentes\": \"Mama ven a buscarme\",\n    \"ident\": \"02\",\n    \"state\": true,\n    \"subject\": \"cancelacion de plan de datos\"\n}"
            ]
        },
        {
            "ejecutivo": "",
            "nombre": "Superman",
            "rut": "888888888",
            "solicitudes": [
                "{\n    \"antecedentes\": \"\",\n    \"ident\": \"01\",\n    \"state\": true,\n    \"subject\": \"actualizacion de plan de internet\"\n}",
                "{\n    \"antecedentes\": \"\",\n    \"ident\": \"02\",\n    \"state\": true,\n    \"subject\": \"cambio de clave wifi\"\n}"
            ]
        },{
            "ejecutivo": "",
            "nombre": "Geralt de Rivia",
            "rut": "222222222",
            "solicitudes": [
                "{\n    \"antecedentes\": \"tu nueva clave es JIJIJAJA\",\n    \"ident\": \"01\",\n    \"state\": true,\n    \"subject\": \"cambio de clave wifi\"\n}",
                "{\n    \"antecedentes\": \"mama ven a buscarme\",\n    \"ident\": \"02\",\n    \"state\": true,\n    \"subject\": \"cancelacion de plan de datos\"\n}"
            ]
        },
        {
            "ejecutivo": "",
            "nombre": "Mario Hugo",
            "rut": "999999999",
            "solicitudes": [
                "{\n    \"antecedentes\": \"\",\n    \"ident\": \"01\",\n    \"state\": true,\n    \"subject\": \"actualizacion de plan de internet\"\n}",
                "{\n    \"antecedentes\": \"\",\n    \"ident\": \"02\",\n    \"state\": true,\n    \"subject\": \"cambio de clave wifi\"\n}"
            ]
        }
    ]
}